[{"id":1,"basin_directorate":"БДДР","name":"Искър","total_volume":655.252,"sanitary_volume":87.2,"current_volume":491.285,"current_volume_percent":74.98,"current_useful_volume":404.085,"current_useful_volume_percent":71.14,"ingress":7.068,"egress":16.136,"trend":"↓"},{"id":2,"basin_directorate":"БДДР","name":"Бели Искър","total_volume":15.08,"sanitary_volume":1.4,"current_volume":8.38,"current_volume_percent":55.57,"current_useful_volume":6.98,"current_useful_volume_percent":51.02,"ingress":0.002,"egress":0.813,"trend":"↓"},{"id":3,"basin_directorate":"БДДР","name":"Среченска бара","total_volume":15.5,"sanitary_volume":1.0,"current_volume":15.056,"current_volume_percent":97.14,"current_useful_volume":14.056,"current_useful_volume_percent":96.94,"ingress":0.694,"egress":0.475,"trend":"↑"},{"id":4,"basin_directorate":"БДДР","name":"Христо Смирненски","total_volume":27.7,"sanitary_volume":4.2,"current_volume":24.235,"current_volume_percent":87.49,"current_useful_volume":20.035,"current_useful_volume_percent":85.26,"ingress":0.945,"egress":1.383,"trend":"↓"},{"id":5,"basin_directorate":"БДДР","name":"Йовковци","total_volume":92.179,"sanitary_volume":9.0,"current_volume":82.616,"current_volume_percent":89.63,"current_useful_volume":73.616,"current_useful_volume_percent":88.5,"ingress":1.311,"egress":0.696,"trend":"↑"},{"id":6,"basin_directorate":"БДЧР","name":"Тича","total_volume":311.8,"sanitary_volume":40.0,"current_volume":235.444,"current_volume_percent":75.51,"current_useful_volume":195.444,"current_useful_volume_percent":71.91,"ingress":5.228,"egress":1.431,"trend":"↑"},{"id":7,"basin_directorate":"БДЧР","name":"Камчия","total_volume":233.55,"sanitary_volume":76.0,"current_volume":223.938,"current_volume_percent":95.88,"current_useful_volume":147.938,"current_useful_volume_percent":93.9,"ingress":6.771,"egress":2.303,"trend":"↑"},{"id":8,"basin_directorate":"БДЧР","name":"Ясна поляна","total_volume":32.32,"sanitary_volume":7.55,"current_volume":25.239,"current_volume_percent":78.09,"current_useful_volume":17.689,"current_useful_volume_percent":71.41,"ingress":5.961,"egress":0.382,"trend":"↑"},{"id":9,"basin_directorate":"БДИБР","name":"Асеновец","total_volume":28.2,"sanitary_volume":2.0,"current_volume":20.296,"current_volume_percent":71.97,"current_useful_volume":18.296,"current_useful_volume_percent":69.83,"ingress":1.007,"egress":0.822,"trend":"↑"},{"id":10,"basin_directorate":"БДИБР","name":"Боровица","total_volume":27.3,"sanitary_volume":4.6,"current_volume":27.24,"current_volume_percent":99.78,"current_useful_volume":22.64,"current_useful_volume_percent":99.74,"ingress":0.3,"egress":0.3,"trend":"~"},{"id":11,"basin_directorate":"БДЗБР","name":"Студена","total_volume":25.2,"sanitary_volume":2.4,"current_volume":19.196,"current_volume_percent":76.17,"current_useful_volume":16.796,"current_useful_volume_percent":73.67,"ingress":0.743,"egress":0.743,"trend":"~"},{"id":12,"basin_directorate":"БДЗБР","name":"Дяково","total_volume":35.4,"sanitary_volume":8.0,"current_volume":25.475,"current_volume_percent":71.96,"current_useful_volume":17.475,"current_useful_volume_percent":63.78,"ingress":0.0,"egress":0.585,"trend":"↓"},{"id":13,"basin_directorate":"БДЗБР","name":"Калин - за рез.водоснабдяване","total_volume":1.024,"sanitary_volume":0.1,"current_volume":0.313,"current_volume_percent":30.57,"current_useful_volume":0.213,"current_useful_volume_percent":23.05,"ingress":null,"egress":null,"trend":"↑"},{"id":14,"basin_directorate":"БДЗБР","name":"Карагьол - за рез.водоснабдяване","total_volume":2.252,"sanitary_volume":0.2,"current_volume":0.378,"current_volume_percent":16.78,"current_useful_volume":0.178,"current_useful_volume_percent":8.67,"ingress":null,"egress":null,"trend":"д"},{"id":15,"basin_directorate":"БДДР","name":"Огняново - за рез.водоснабдяване **","total_volume":31.6,"sanitary_volume":2.5,"current_volume":19.358,"current_volume_percent":61.26,"current_useful_volume":16.858,"current_useful_volume_percent":57.93,"ingress":0.853,"egress":1.05,"trend":"↓"},{"id":16,"basin_directorate":"БДДР","name":"Панчарево","total_volume":6.465,"sanitary_volume":1.5,"current_volume":5.072,"current_volume_percent":78.45,"current_useful_volume":3.572,"current_useful_volume_percent":71.94,"ingress":17.67,"egress":16.466,"trend":"᷆"},{"id":17,"basin_directorate":"БДДР","name":"Ястребино","total_volume":62.3,"sanitary_volume":3.9,"current_volume":42.363,"current_volume_percent":68.0,"current_useful_volume":38.463,"current_useful_volume_percent":65.86,"ingress":4.722,"egress":0.104,"trend":"↑"},{"id":18,"basin_directorate":"БДДР","name":"Кула","total_volume":20.25,"sanitary_volume":0.7,"current_volume":8.86,"current_volume_percent":43.75,"current_useful_volume":8.16,"current_useful_volume_percent":41.74,"ingress":0.116,"egress":0.116,"trend":"~"},{"id":19,"basin_directorate":"БДДР","name":"Рабиша","total_volume":43.2,"sanitary_volume":2.4,"current_volume":11.684,"current_volume_percent":27.05,"current_useful_volume":9.284,"current_useful_volume_percent":22.75,"ingress":0.0,"egress":0.0,"trend":"~"},{"id":20,"basin_directorate":"БДДР","name":"Огоста","total_volume":506.0,"sanitary_volume":67.0,"current_volume":196.42,"current_volume_percent":38.82,"current_useful_volume":129.42,"current_useful_volume_percent":29.48,"ingress":2.315,"egress":3.704,"trend":"↓"},{"id":21,"basin_directorate":"БДДР","name":"Сопот","total_volume":60.908,"sanitary_volume":1.3,"current_volume":35.734,"current_volume_percent":58.67,"current_useful_volume":34.434,"current_useful_volume_percent":57.77,"ingress":2.303,"egress":0.394,"trend":"↑"},{"id":22,"basin_directorate":"БДДР","name":"Горни Дъбник","total_volume":130.0,"sanitary_volume":3.0,"current_volume":55.478,"current_volume_percent":42.68,"current_useful_volume":52.478,"current_useful_volume_percent":41.32,"ingress":1.933,"egress":0.486,"trend":"↑"},{"id":23,"basin_directorate":"БДДР","name":"Бели Лом","total_volume":25.5,"sanitary_volume":3.2,"current_volume":9.414,"current_volume_percent":36.92,"current_useful_volume":6.214,"current_useful_volume_percent":27.87,"ingress":0.081,"egress":0.081,"trend":"~"},{"id":24,"basin_directorate":"БДЧР","name":"Съединение","total_volume":12.81,"sanitary_volume":1.5,"current_volume":8.339,"current_volume_percent":65.1,"current_useful_volume":6.839,"current_useful_volume_percent":60.47,"ingress":0.069,"egress":0.069,"trend":"~"},{"id":25,"basin_directorate":"БДЧР","name":"Георги Трайков (Цонево)","total_volume":330.0,"sanitary_volume":21.0,"current_volume":172.382,"current_volume_percent":52.24,"current_useful_volume":151.382,"current_useful_volume_percent":48.99,"ingress":3.36,"egress":1.856,"trend":"↑"},{"id":26,"basin_directorate":"БДЧР","name":"Порой","total_volume":45.2,"sanitary_volume":2.0,"current_volume":5.115,"current_volume_percent":11.32,"current_useful_volume":3.115,"current_useful_volume_percent":7.21,"ingress":0.532,"egress":0.0,"trend":"↑"},{"id":27,"basin_directorate":"БДЧР","name":"Ахелой","total_volume":12.35,"sanitary_volume":0.8,"current_volume":2.568,"current_volume_percent":20.79,"current_useful_volume":1.768,"current_useful_volume_percent":15.31,"ingress":0.092,"egress":0.0,"trend":"↑"},{"id":28,"basin_directorate":"БДИБР","name":"Жребчево","total_volume":400.0,"sanitary_volume":30.0,"current_volume":220.128,"current_volume_percent":55.03,"current_useful_volume":190.128,"current_useful_volume_percent":51.39,"ingress":3.249,"egress":1.49,"trend":"↑"},{"id":29,"basin_directorate":"БДИБР","name":"Малко Шарково","total_volume":45.0,"sanitary_volume":3.9,"current_volume":37.994,"current_volume_percent":84.43,"current_useful_volume":34.094,"current_useful_volume_percent":82.95,"ingress":2.005,"egress":2.005,"trend":"~"},{"id":30,"basin_directorate":"БДИБР","name":"Домлян","total_volume":26.074,"sanitary_volume":0.7,"current_volume":11.935,"current_volume_percent":45.77,"current_useful_volume":11.235,"current_useful_volume_percent":44.28,"ingress":0.442,"egress":0.087,"trend":"↑"},{"id":31,"basin_directorate":"БДИБР","name":"Пясъчник","total_volume":206.53,"sanitary_volume":3.4,"current_volume":37.5,"current_volume_percent":18.16,"current_useful_volume":34.1,"current_useful_volume_percent":16.79,"ingress":1.951,"egress":0.215,"trend":"↑"},{"id":32,"basin_directorate":"БДИБР","name":"Тополница","total_volume":137.108,"sanitary_volume":20.0,"current_volume":95.305,"current_volume_percent":69.51,"current_useful_volume":75.305,"current_useful_volume_percent":64.3,"ingress":8.981,"egress":10.544,"trend":"↓"},{"id":33,"basin_directorate":"БДИБР","name":"Тракиец","total_volume":114.0,"sanitary_volume":24.0,"current_volume":73.86,"current_volume_percent":64.79,"current_useful_volume":49.86,"current_useful_volume_percent":55.4,"ingress":2.141,"egress":2.141,"trend":"~"},{"id":34,"basin_directorate":"БДЗБР","name":"Пчелина","total_volume":54.2,"sanitary_volume":34.2,"current_volume":54.1,"current_volume_percent":99.82,"current_useful_volume":19.9,"current_useful_volume_percent":99.5,"ingress":7.407,"egress":7.407,"trend":"᷆"},{"id":35,"basin_directorate":"БДДР","name":"Александър Стамболийски","total_volume":205.569,"sanitary_volume":20.0,"current_volume":127.98,"current_volume_percent":62.26,"current_useful_volume":107.98,"current_useful_volume_percent":58.19,"ingress":9.268,"egress":0.949,"trend":"↑"},{"id":36,"basin_directorate":"БДДР","name":"Кокаляне","total_volume":null,"sanitary_volume":null,"current_volume":null,"current_volume_percent":null,"current_useful_volume":null,"current_useful_volume_percent":null,"ingress":null,"egress":null,"trend":null},{"id":37,"basin_directorate":"БДИБР","name":"Копринка","total_volume":142.214,"sanitary_volume":5.41,"current_volume":67.856,"current_volume_percent":47.71,"current_useful_volume":62.446,"current_useful_volume_percent":45.65,"ingress":4.055,"egress":0.96,"trend":"↑"},{"id":38,"basin_directorate":"БДИБР","name":"Белмекен","total_volume":144.036,"sanitary_volume":3.81,"current_volume":66.272,"current_volume_percent":46.01,"current_useful_volume":62.462,"current_useful_volume_percent":44.54,"ingress":null,"egress":null,"trend":"↓"},{"id":39,"basin_directorate":"БДИБР","name":"Чаира","total_volume":5.5,"sanitary_volume":1.369,"current_volume":2.338,"current_volume_percent":42.51,"current_useful_volume":0.969,"current_useful_volume_percent":23.46,"ingress":null,"egress":null,"trend":"↑"},{"id":40,"basin_directorate":"БДИБР","name":"Голям Беглик","total_volume":62.111,"sanitary_volume":3.942,"current_volume":42.946,"current_volume_percent":69.14,"current_useful_volume":39.004,"current_useful_volume_percent":67.05,"ingress":null,"egress":null,"trend":"↓"},{"id":41,"basin_directorate":"БДИБР","name":"Широка поляна","total_volume":23.98,"sanitary_volume":3.3,"current_volume":10.192,"current_volume_percent":42.5,"current_useful_volume":6.892,"current_useful_volume_percent":33.33,"ingress":null,"egress":null,"trend":"↓"},{"id":42,"basin_directorate":"БДИБР","name":"Беглика","total_volume":1.554,"sanitary_volume":0.242,"current_volume":0.958,"current_volume_percent":61.64,"current_useful_volume":0.716,"current_useful_volume_percent":54.57,"ingress":0.189,"egress":0.475,"trend":"↓"},{"id":43,"basin_directorate":"БДИБР","name":"Тошков Чарк","total_volume":1.782,"sanitary_volume":0.276,"current_volume":0.708,"current_volume_percent":39.71,"current_useful_volume":0.432,"current_useful_volume_percent":28.67,"ingress":0.296,"egress":0.438,"trend":"↓"},{"id":44,"basin_directorate":"БДИБР","name":"Батак","total_volume":310.298,"sanitary_volume":19.95,"current_volume":225.723,"current_volume_percent":72.74,"current_useful_volume":205.773,"current_useful_volume_percent":70.87,"ingress":8.314,"egress":3.993,"trend":"↑"},{"id":45,"basin_directorate":"БДЗБР","name":"Доспат","total_volume":449.249,"sanitary_volume":14.907,"current_volume":369.323,"current_volume_percent":82.21,"current_useful_volume":354.416,"current_useful_volume_percent":81.6,"ingress":3.616,"egress":3.616,"trend":"~"},{"id":46,"basin_directorate":"БДИБР","name":"Цанков камък","total_volume":110.708,"sanitary_volume":31.2,"current_volume":81.535,"current_volume_percent":73.65,"current_useful_volume":50.335,"current_useful_volume_percent":63.31,"ingress":9.377,"egress":8.208,"trend":"↑"},{"id":47,"basin_directorate":"БДИБР","name":"Въча","total_volume":226.12,"sanitary_volume":24.52,"current_volume":185.342,"current_volume_percent":81.97,"current_useful_volume":160.822,"current_useful_volume_percent":79.77,"ingress":9.775,"egress":7.287,"trend":"↑"},{"id":48,"basin_directorate":"БДИБР","name":"Кричим","total_volume":20.256,"sanitary_volume":1.73,"current_volume":19.684,"current_volume_percent":97.18,"current_useful_volume":17.954,"current_useful_volume_percent":96.91,"ingress":6.972,"egress":5.375,"trend":"↑"},{"id":49,"basin_directorate":"БДИБР","name":"Кърджали","total_volume":497.236,"sanitary_volume":107.176,"current_volume":350.872,"current_volume_percent":70.56,"current_useful_volume":243.696,"current_useful_volume_percent":62.48,"ingress":24.906,"egress":53.709,"trend":"↓"},{"id":50,"basin_directorate":"БДИБР","name":"Студен кладенец","total_volume":387.772,"sanitary_volume":90.667,"current_volume":266.839,"current_volume_percent":68.81,"current_useful_volume":176.172,"current_useful_volume_percent":59.3,"ingress":81.294,"egress":113.061,"trend":"↓"},{"id":51,"basin_directorate":"БДИБР","name":"Ивайловград","total_volume":156.702,"sanitary_volume":59.526,"current_volume":108.941,"current_volume_percent":69.52,"current_useful_volume":49.415,"current_useful_volume_percent":50.85,"ingress":140.308,"egress":142.929,"trend":"↓"},{"id":52,"basin_directorate":"БДИБР","name":"Розов кладенец","total_volume":20.4,"sanitary_volume":13.268,"current_volume":18.924,"current_volume_percent":92.76,"current_useful_volume":5.656,"current_useful_volume_percent":79.3,"ingress":null,"egress":null,"trend":"↓"}]