[{"id":1,"basin_directorate":"БДДР","name":"Искър","total_volume":655.252,"sanitary_volume":87.2,"current_volume":532.583,"current_volume_percent":81.28,"current_useful_volume":445.383,"current_useful_volume_percent":78.41,"ingress":2.115,"egress":9.936,"trend":"↓"},{"id":2,"basin_directorate":"БДДР","name":"Бели Искър","total_volume":15.08,"sanitary_volume":1.4,"current_volume":8.949,"current_volume_percent":59.34,"current_useful_volume":7.549,"current_useful_volume_percent":55.18,"ingress":0.31,"egress":0.46,"trend":"↓"},{"id":3,"basin_directorate":"БДДР","name":"Среченска бара","total_volume":15.5,"sanitary_volume":1.0,"current_volume":14.413,"current_volume_percent":92.99,"current_useful_volume":13.413,"current_useful_volume_percent":92.5,"ingress":0.498,"egress":0.602,"trend":"↓"},{"id":4,"basin_directorate":"БДДР","name":"Христо Смирненски","total_volume":27.7,"sanitary_volume":4.2,"current_volume":18.941,"current_volume_percent":68.38,"current_useful_volume":14.741,"current_useful_volume_percent":62.73,"ingress":0.091,"egress":0.332,"trend":"↓"},{"id":5,"basin_directorate":"БДДР","name":"Йовковци","total_volume":92.179,"sanitary_volume":9.0,"current_volume":81.769,"current_volume_percent":88.71,"current_useful_volume":72.769,"current_useful_volume_percent":87.48,"ingress":0.105,"egress":0.715,"trend":"↓"},{"id":6,"basin_directorate":"БДЧР","name":"Тича","total_volume":311.8,"sanitary_volume":40.0,"current_volume":229.376,"current_volume_percent":73.57,"current_useful_volume":189.376,"current_useful_volume_percent":69.67,"ingress":0.144,"egress":1.852,"trend":"↓"},{"id":7,"basin_directorate":"БДЧР","name":"Камчия","total_volume":233.55,"sanitary_volume":76.0,"current_volume":190.411,"current_volume_percent":81.53,"current_useful_volume":114.411,"current_useful_volume_percent":72.62,"ingress":0.018,"egress":1.592,"trend":"↓"},{"id":8,"basin_directorate":"БДЧР","name":"Ясна поляна","total_volume":32.32,"sanitary_volume":7.55,"current_volume":17.005,"current_volume_percent":52.61,"current_useful_volume":9.455,"current_useful_volume_percent":38.17,"ingress":0.012,"egress":0.324,"trend":"↓"},{"id":9,"basin_directorate":"БДИБР","name":"Асеновец","total_volume":28.2,"sanitary_volume":2.0,"current_volume":15.907,"current_volume_percent":56.41,"current_useful_volume":13.907,"current_useful_volume_percent":53.08,"ingress":0.046,"egress":0.741,"trend":"↓"},{"id":10,"basin_directorate":"БДИБР","name":"Боровица","total_volume":27.3,"sanitary_volume":4.6,"current_volume":24.086,"current_volume_percent":88.23,"current_useful_volume":19.486,"current_useful_volume_percent":85.84,"ingress":0.023,"egress":0.37,"trend":"↓"},{"id":11,"basin_directorate":"БДЗБР","name":"Студена","total_volume":25.2,"sanitary_volume":2.4,"current_volume":20.451,"current_volume_percent":81.15,"current_useful_volume":18.051,"current_useful_volume_percent":79.17,"ingress":0.288,"egress":0.764,"trend":"↓"},{"id":12,"basin_directorate":"БДЗБР","name":"Дяково","total_volume":35.4,"sanitary_volume":8.0,"current_volume":27.795,"current_volume_percent":78.52,"current_useful_volume":19.795,"current_useful_volume_percent":72.25,"ingress":0.058,"egress":0.236,"trend":"↓"},{"id":13,"basin_directorate":"БДЗБР","name":"Калин - за рез.водоснабдяване","total_volume":1.024,"sanitary_volume":0.1,"current_volume":0.471,"current_volume_percent":46.02,"current_useful_volume":0.371,"current_useful_volume_percent":40.17,"ingress":null,"egress":null,"trend":"↓"},{"id":14,"basin_directorate":"БДЗБР","name":"Карагьол - за рез.водоснабдяване","total_volume":2.252,"sanitary_volume":0.2,"current_volume":1.781,"current_volume_percent":79.06,"current_useful_volume":1.581,"current_useful_volume_percent":77.02,"ingress":null,"egress":null,"trend":"д"},{"id":15,"basin_directorate":"БДДР","name":"Огняново - за рез.водоснабдяване **","total_volume":31.6,"sanitary_volume":2.5,"current_volume":17.377,"current_volume_percent":54.99,"current_useful_volume":14.877,"current_useful_volume_percent":51.12,"ingress":0.185,"egress":0.335,"trend":"↓"},{"id":16,"basin_directorate":"БДДР","name":"Панчарево","total_volume":6.465,"sanitary_volume":1.5,"current_volume":5.31,"current_volume_percent":82.13,"current_useful_volume":3.81,"current_useful_volume_percent":76.73,"ingress":8.87,"egress":9.689,"trend":"᷆"},{"id":17,"basin_directorate":"БДДР","name":"Ястребино","total_volume":62.3,"sanitary_volume":3.9,"current_volume":33.941,"current_volume_percent":54.48,"current_useful_volume":30.041,"current_useful_volume_percent":51.44,"ingress":0.104,"egress":0.104,"trend":"~"},{"id":18,"basin_directorate":"БДДР","name":"Кула","total_volume":20.25,"sanitary_volume":0.7,"current_volume":7.461,"current_volume_percent":36.84,"current_useful_volume":6.761,"current_useful_volume_percent":34.58,"ingress":0.0,"egress":0.127,"trend":"↓"},{"id":19,"basin_directorate":"БДДР","name":"Рабиша","total_volume":43.2,"sanitary_volume":2.4,"current_volume":12.543,"current_volume_percent":29.03,"current_useful_volume":10.143,"current_useful_volume_percent":24.86,"ingress":0.0,"egress":0.023,"trend":"↓"},{"id":20,"basin_directorate":"БДДР","name":"Огоста","total_volume":506.0,"sanitary_volume":67.0,"current_volume":217.855,"current_volume_percent":43.05,"current_useful_volume":150.855,"current_useful_volume_percent":34.36,"ingress":0.116,"egress":6.25,"trend":"↓"},{"id":21,"basin_directorate":"БДДР","name":"Сопот","total_volume":60.908,"sanitary_volume":1.3,"current_volume":29.21,"current_volume_percent":47.96,"current_useful_volume":27.91,"current_useful_volume_percent":46.82,"ingress":0.59,"egress":2.211,"trend":"↓"},{"id":22,"basin_directorate":"БДДР","name":"Горни Дъбник","total_volume":130.0,"sanitary_volume":3.0,"current_volume":47.098,"current_volume_percent":36.23,"current_useful_volume":44.098,"current_useful_volume_percent":34.72,"ingress":1.007,"egress":1.007,"trend":"~"},{"id":23,"basin_directorate":"БДДР","name":"Бели Лом","total_volume":25.5,"sanitary_volume":3.2,"current_volume":8.459,"current_volume_percent":33.17,"current_useful_volume":5.259,"current_useful_volume_percent":23.58,"ingress":0.069,"egress":0.069,"trend":"~"},{"id":24,"basin_directorate":"БДЧР","name":"Съединение","total_volume":12.81,"sanitary_volume":1.5,"current_volume":8.196,"current_volume_percent":63.98,"current_useful_volume":6.696,"current_useful_volume_percent":59.2,"ingress":0.081,"egress":0.081,"trend":"~"},{"id":25,"basin_directorate":"БДЧР","name":"Георги Трайков (Цонево)","total_volume":330.0,"sanitary_volume":21.0,"current_volume":177.454,"current_volume_percent":53.77,"current_useful_volume":156.454,"current_useful_volume_percent":50.63,"ingress":0.005,"egress":3.014,"trend":"↓"},{"id":26,"basin_directorate":"БДЧР","name":"Порой","total_volume":45.2,"sanitary_volume":2.0,"current_volume":4.557,"current_volume_percent":10.08,"current_useful_volume":2.557,"current_useful_volume_percent":5.92,"ingress":0.046,"egress":0.0,"trend":"↑"},{"id":27,"basin_directorate":"БДЧР","name":"Ахелой","total_volume":12.35,"sanitary_volume":0.8,"current_volume":2.782,"current_volume_percent":22.53,"current_useful_volume":1.982,"current_useful_volume_percent":17.16,"ingress":0.023,"egress":0.0,"trend":"↑"},{"id":28,"basin_directorate":"БДИБР","name":"Жребчево","total_volume":400.0,"sanitary_volume":30.0,"current_volume":149.7,"current_volume_percent":37.43,"current_useful_volume":119.7,"current_useful_volume_percent":32.35,"ingress":2.44,"egress":2.44,"trend":"~"},{"id":29,"basin_directorate":"БДИБР","name":"Малко Шарково","total_volume":45.0,"sanitary_volume":3.9,"current_volume":32.947,"current_volume_percent":73.22,"current_useful_volume":29.047,"current_useful_volume_percent":70.67,"ingress":0.032,"egress":0.344,"trend":"↓"},{"id":30,"basin_directorate":"БДИБР","name":"Домлян","total_volume":26.074,"sanitary_volume":0.7,"current_volume":6.516,"current_volume_percent":24.99,"current_useful_volume":5.816,"current_useful_volume_percent":22.92,"ingress":0.0,"egress":0.084,"trend":"↓"},{"id":31,"basin_directorate":"БДИБР","name":"Пясъчник","total_volume":206.53,"sanitary_volume":3.4,"current_volume":34.05,"current_volume_percent":16.49,"current_useful_volume":30.65,"current_useful_volume_percent":15.09,"ingress":0.203,"egress":0.203,"trend":"~"},{"id":32,"basin_directorate":"БДИБР","name":"Тополница","total_volume":137.108,"sanitary_volume":20.0,"current_volume":34.392,"current_volume_percent":25.08,"current_useful_volume":14.392,"current_useful_volume_percent":12.29,"ingress":1.308,"egress":0.556,"trend":"↑"},{"id":33,"basin_directorate":"БДИБР","name":"Тракиец","total_volume":114.0,"sanitary_volume":24.0,"current_volume":64.408,"current_volume_percent":56.5,"current_useful_volume":40.408,"current_useful_volume_percent":44.9,"ingress":0.006,"egress":0.197,"trend":"↓"},{"id":34,"basin_directorate":"БДЗБР","name":"Пчелина","total_volume":54.2,"sanitary_volume":34.2,"current_volume":53.9,"current_volume_percent":99.45,"current_useful_volume":19.7,"current_useful_volume_percent":98.5,"ingress":3.438,"egress":3.438,"trend":"᷆"},{"id":35,"basin_directorate":"БДДР","name":"Александър Стамболийски","total_volume":205.569,"sanitary_volume":20.0,"current_volume":121.592,"current_volume_percent":59.15,"current_useful_volume":101.592,"current_useful_volume_percent":54.75,"ingress":0.159,"egress":1.058,"trend":"↓"},{"id":36,"basin_directorate":"БДДР","name":"Кокаляне","total_volume":null,"sanitary_volume":null,"current_volume":null,"current_volume_percent":null,"current_useful_volume":null,"current_useful_volume_percent":null,"ingress":null,"egress":null,"trend":null},{"id":37,"basin_directorate":"БДИБР","name":"Копринка","total_volume":142.214,"sanitary_volume":5.41,"current_volume":19.303,"current_volume_percent":13.57,"current_useful_volume":13.893,"current_useful_volume_percent":10.16,"ingress":1.471,"egress":1.158,"trend":"↑"},{"id":38,"basin_directorate":"БДИБР","name":"Белмекен","total_volume":144.036,"sanitary_volume":3.81,"current_volume":99.082,"current_volume_percent":68.79,"current_useful_volume":95.272,"current_useful_volume_percent":67.94,"ingress":null,"egress":null,"trend":"↓"},{"id":40,"basin_directorate":"БДИБР","name":"Голям Беглик","total_volume":62.111,"sanitary_volume":3.942,"current_volume":40.955,"current_volume_percent":65.94,"current_useful_volume":37.013,"current_useful_volume_percent":63.63,"ingress":null,"egress":null,"trend":"↓"},{"id":41,"basin_directorate":"БДИБР","name":"Широка поляна","total_volume":23.98,"sanitary_volume":3.3,"current_volume":8.819,"current_volume_percent":36.78,"current_useful_volume":5.519,"current_useful_volume_percent":26.69,"ingress":null,"egress":null,"trend":"↓"},{"id":42,"basin_directorate":"БДИБР","name":"Беглика","total_volume":1.554,"sanitary_volume":0.242,"current_volume":0.985,"current_volume_percent":63.39,"current_useful_volume":0.743,"current_useful_volume_percent":56.64,"ingress":0.062,"egress":0.005,"trend":"↑"},{"id":43,"basin_directorate":"БДИБР","name":"Тошков Чарк","total_volume":1.782,"sanitary_volume":0.276,"current_volume":0.668,"current_volume_percent":37.48,"current_useful_volume":0.392,"current_useful_volume_percent":26.02,"ingress":0.306,"egress":0.253,"trend":"↑"},{"id":44,"basin_directorate":"БДИБР","name":"Батак","total_volume":310.298,"sanitary_volume":19.95,"current_volume":180.746,"current_volume_percent":58.25,"current_useful_volume":160.796,"current_useful_volume_percent":55.38,"ingress":4.772,"egress":0.514,"trend":"↑"},{"id":45,"basin_directorate":"БДЗБР","name":"Доспат","total_volume":449.249,"sanitary_volume":14.907,"current_volume":342.601,"current_volume_percent":76.26,"current_useful_volume":327.694,"current_useful_volume_percent":75.45,"ingress":0.797,"egress":0.797,"trend":"~"},{"id":46,"basin_directorate":"БДИБР","name":"Цанков камък","total_volume":110.708,"sanitary_volume":31.2,"current_volume":86.042,"current_volume_percent":77.72,"current_useful_volume":54.842,"current_useful_volume_percent":68.98,"ingress":4.459,"egress":1.389,"trend":"↑"},{"id":47,"basin_directorate":"БДИБР","name":"Въча","total_volume":226.12,"sanitary_volume":24.52,"current_volume":157.925,"current_volume_percent":69.84,"current_useful_volume":133.405,"current_useful_volume_percent":66.17,"ingress":2.209,"egress":15.496,"trend":"↓"},{"id":48,"basin_directorate":"БДИБР","name":"Кричим","total_volume":20.256,"sanitary_volume":1.73,"current_volume":19.78,"current_volume_percent":97.65,"current_useful_volume":18.05,"current_useful_volume_percent":97.43,"ingress":14.93,"egress":12.925,"trend":"↑"},{"id":49,"basin_directorate":"БДИБР","name":"Кърджали","total_volume":497.236,"sanitary_volume":107.176,"current_volume":284.226,"current_volume_percent":57.16,"current_useful_volume":177.05,"current_useful_volume_percent":45.39,"ingress":2.18,"egress":26.884,"trend":"↓"},{"id":50,"basin_directorate":"БДИБР","name":"Студен кладенец","total_volume":387.772,"sanitary_volume":90.667,"current_volume":233.509,"current_volume_percent":60.22,"current_useful_volume":142.842,"current_useful_volume_percent":48.08,"ingress":25.74,"egress":21.152,"trend":"↑"},{"id":51,"basin_directorate":"БДИБР","name":"Ивайловград","total_volume":156.702,"sanitary_volume":59.526,"current_volume":137.142,"current_volume_percent":87.52,"current_useful_volume":77.616,"current_useful_volume_percent":79.87,"ingress":19.158,"egress":40.308,"trend":"↓"},{"id":52,"basin_directorate":"БДИБР","name":"Розов кладенец","total_volume":20.4,"sanitary_volume":13.268,"current_volume":17.196,"current_volume_percent":84.29,"current_useful_volume":3.928,"current_useful_volume_percent":55.08,"ingress":null,"egress":null,"trend":"↑"}]