[{"id":1,"basin_directorate":"БДДР","name":"Искър","total_volume":655.252,"sanitary_volume":87.2,"current_volume":526.249,"current_volume_percent":80.31,"current_useful_volume":439.049,"current_useful_volume_percent":77.29,"ingress":8.073,"egress":22.081,"trend":"↓"},{"id":2,"basin_directorate":"БДДР","name":"Бели Искър","total_volume":15.08,"sanitary_volume":1.4,"current_volume":11.32,"current_volume_percent":75.07,"current_useful_volume":9.92,"current_useful_volume_percent":72.51,"ingress":0.782,"egress":1.039,"trend":"↓"},{"id":3,"basin_directorate":"БДДР","name":"Среченска бара","total_volume":15.5,"sanitary_volume":1.0,"current_volume":15.27,"current_volume_percent":98.52,"current_useful_volume":14.27,"current_useful_volume_percent":98.41,"ingress":0.544,"egress":0.544,"trend":"~"},{"id":4,"basin_directorate":"БДДР","name":"Христо Смирненски","total_volume":27.7,"sanitary_volume":4.2,"current_volume":25.396,"current_volume_percent":91.68,"current_useful_volume":21.196,"current_useful_volume_percent":90.2,"ingress":0.155,"egress":1.47,"trend":"↓"},{"id":5,"basin_directorate":"БДДР","name":"Йовковци","total_volume":92.179,"sanitary_volume":9.0,"current_volume":73.934,"current_volume_percent":80.21,"current_useful_volume":64.934,"current_useful_volume_percent":78.07,"ingress":0.614,"egress":0.614,"trend":"~"},{"id":6,"basin_directorate":"БДЧР","name":"Тича","total_volume":311.8,"sanitary_volume":40.0,"current_volume":147.906,"current_volume_percent":47.44,"current_useful_volume":107.906,"current_useful_volume_percent":39.7,"ingress":1.154,"egress":1.154,"trend":"~"},{"id":7,"basin_directorate":"БДЧР","name":"Камчия","total_volume":233.55,"sanitary_volume":76.0,"current_volume":165.5,"current_volume_percent":70.86,"current_useful_volume":89.5,"current_useful_volume_percent":56.81,"ingress":7.303,"egress":1.898,"trend":"↑"},{"id":8,"basin_directorate":"БДЧР","name":"Ясна поляна","total_volume":32.32,"sanitary_volume":7.55,"current_volume":22.108,"current_volume_percent":68.4,"current_useful_volume":14.558,"current_useful_volume_percent":58.77,"ingress":0.174,"egress":0.335,"trend":"↓"},{"id":9,"basin_directorate":"БДИБР","name":"Асеновец","total_volume":28.2,"sanitary_volume":2.0,"current_volume":15.853,"current_volume_percent":56.22,"current_useful_volume":13.853,"current_useful_volume_percent":52.87,"ingress":1.563,"egress":0.174,"trend":"↑"},{"id":10,"basin_directorate":"БДИБР","name":"Боровица","total_volume":27.3,"sanitary_volume":4.6,"current_volume":27.175,"current_volume_percent":99.54,"current_useful_volume":22.575,"current_useful_volume_percent":99.45,"ingress":8.091,"egress":8.38,"trend":"↓"},{"id":11,"basin_directorate":"БДЗБР","name":"Студена","total_volume":25.2,"sanitary_volume":2.4,"current_volume":21.24,"current_volume_percent":84.29,"current_useful_volume":18.84,"current_useful_volume_percent":82.63,"ingress":0.326,"egress":3.162,"trend":"↓"},{"id":12,"basin_directorate":"БДЗБР","name":"Дяково","total_volume":35.4,"sanitary_volume":8.0,"current_volume":30.7,"current_volume_percent":86.72,"current_useful_volume":22.7,"current_useful_volume_percent":82.85,"ingress":0.326,"egress":0.136,"trend":"↑"},{"id":13,"basin_directorate":"БДЗБР","name":"","total_volume":1.024,"sanitary_volume":0.1,"current_volume":0.294,"current_volume_percent":28.71,"current_useful_volume":0.194,"current_useful_volume_percent":21.0,"ingress":null,"egress":null,"trend":"~"},{"id":14,"basin_directorate":"БДЗБР","name":"","total_volume":2.252,"sanitary_volume":0.2,"current_volume":1.411,"current_volume_percent":62.65,"current_useful_volume":1.211,"current_useful_volume_percent":59.01,"ingress":null,"egress":null,"trend":"~"},{"id":15,"basin_directorate":"БДДР","name":"","total_volume":31.6,"sanitary_volume":2.5,"current_volume":19.887,"current_volume_percent":62.93,"current_useful_volume":17.387,"current_useful_volume_percent":59.75,"ingress":0.189,"egress":0.019,"trend":"↑"},{"id":16,"basin_directorate":"БДДР","name":"","total_volume":6.465,"sanitary_volume":1.5,"current_volume":5.007,"current_volume_percent":77.45,"current_useful_volume":3.507,"current_useful_volume_percent":70.64,"ingress":22.606,"egress":20.004,"trend":"↑"},{"id":17,"basin_directorate":"БДДР","name":"Ястребино","total_volume":62.3,"sanitary_volume":3.9,"current_volume":13.95,"current_volume_percent":22.39,"current_useful_volume":10.05,"current_useful_volume_percent":17.21,"ingress":0.231,"egress":0.035,"trend":"↑"},{"id":18,"basin_directorate":"БДДР","name":"Кула","total_volume":20.25,"sanitary_volume":0.7,"current_volume":7.961,"current_volume_percent":39.31,"current_useful_volume":7.261,"current_useful_volume_percent":37.14,"ingress":0.15,"egress":0.058,"trend":"↑"},{"id":19,"basin_directorate":"БДДР","name":"Рабиша","total_volume":43.2,"sanitary_volume":2.4,"current_volume":12.577,"current_volume_percent":29.11,"current_useful_volume":10.177,"current_useful_volume_percent":24.94,"ingress":0.231,"egress":0.012,"trend":"↑"},{"id":20,"basin_directorate":"БДДР","name":"Огоста","total_volume":506.0,"sanitary_volume":67.0,"current_volume":233.62,"current_volume_percent":46.17,"current_useful_volume":166.62,"current_useful_volume_percent":37.95,"ingress":7.813,"egress":2.257,"trend":"↑"},{"id":21,"basin_directorate":"БДДР","name":"Сопот","total_volume":60.908,"sanitary_volume":1.3,"current_volume":28.8,"current_volume_percent":47.28,"current_useful_volume":27.5,"current_useful_volume_percent":46.13,"ingress":1.088,"egress":0.247,"trend":"↑"},{"id":22,"basin_directorate":"БДДР","name":"Горни Дъбник","total_volume":130.0,"sanitary_volume":3.0,"current_volume":53.754,"current_volume_percent":41.35,"current_useful_volume":50.754,"current_useful_volume_percent":39.96,"ingress":0.961,"egress":0.301,"trend":"↑"},{"id":23,"basin_directorate":"БДДР","name":"Бели Лом","total_volume":25.5,"sanitary_volume":3.2,"current_volume":8.402,"current_volume_percent":32.95,"current_useful_volume":5.202,"current_useful_volume_percent":23.33,"ingress":0.035,"egress":0.035,"trend":"~"},{"id":24,"basin_directorate":"БДЧР","name":"Съединение","total_volume":12.81,"sanitary_volume":1.5,"current_volume":6.022,"current_volume_percent":47.01,"current_useful_volume":4.522,"current_useful_volume_percent":39.98,"ingress":0.023,"egress":0.023,"trend":"~"},{"id":25,"basin_directorate":"БДЧР","name":"Георги Трайков","total_volume":330.0,"sanitary_volume":21.0,"current_volume":125.819,"current_volume_percent":38.13,"current_useful_volume":104.819,"current_useful_volume_percent":33.92,"ingress":3.931,"egress":1.315,"trend":"↑"},{"id":26,"basin_directorate":"БДЧР","name":"Порой","total_volume":45.2,"sanitary_volume":2.0,"current_volume":10.096,"current_volume_percent":22.34,"current_useful_volume":8.096,"current_useful_volume_percent":18.74,"ingress":0.999,"egress":0.166,"trend":"↑"},{"id":27,"basin_directorate":"БДЧР","name":"Ахелой","total_volume":12.67,"sanitary_volume":0.8,"current_volume":3.97,"current_volume_percent":31.33,"current_useful_volume":3.17,"current_useful_volume_percent":26.71,"ingress":0.007,"egress":0.007,"trend":"~"},{"id":28,"basin_directorate":"БДИБР","name":"Жребчево","total_volume":400.0,"sanitary_volume":30.0,"current_volume":171.964,"current_volume_percent":42.99,"current_useful_volume":141.964,"current_useful_volume_percent":38.37,"ingress":19.913,"egress":1.58,"trend":"↑"},{"id":29,"basin_directorate":"БДИБР","name":"Малко Шарково","total_volume":45.0,"sanitary_volume":3.9,"current_volume":27.308,"current_volume_percent":60.68,"current_useful_volume":23.408,"current_useful_volume_percent":56.95,"ingress":1.16,"egress":0.105,"trend":"↑"},{"id":30,"basin_directorate":"БДИБР","name":"Домлян","total_volume":26.074,"sanitary_volume":0.7,"current_volume":13.51,"current_volume_percent":51.81,"current_useful_volume":12.81,"current_useful_volume_percent":50.48,"ingress":1.094,"egress":0.075,"trend":"↑"},{"id":31,"basin_directorate":"БДИБР","name":"Пясъчник","total_volume":206.53,"sanitary_volume":3.4,"current_volume":25.556,"current_volume_percent":12.37,"current_useful_volume":22.156,"current_useful_volume_percent":10.91,"ingress":2.116,"egress":0.171,"trend":"↑"},{"id":32,"basin_directorate":"БДИБР","name":"Тополница","total_volume":137.108,"sanitary_volume":20.0,"current_volume":54.722,"current_volume_percent":39.91,"current_useful_volume":34.722,"current_useful_volume_percent":29.65,"ingress":8.958,"egress":0.694,"trend":"↑"},{"id":33,"basin_directorate":"БДИБР","name":"Тракиец","total_volume":114.0,"sanitary_volume":24.0,"current_volume":71.84,"current_volume_percent":63.02,"current_useful_volume":47.84,"current_useful_volume_percent":53.16,"ingress":0.347,"egress":0.187,"trend":"↑"},{"id":34,"basin_directorate":"БДЗБР","name":"Пчелина","total_volume":54.2,"sanitary_volume":34.2,"current_volume":54.5,"current_volume_percent":100.55,"current_useful_volume":20.3,"current_useful_volume_percent":101.5,"ingress":3.715,"egress":12.03,"trend":"↓"},{"id":35,"basin_directorate":"БДДР","name":"","total_volume":205.569,"sanitary_volume":20.0,"current_volume":152.954,"current_volume_percent":74.41,"current_useful_volume":132.954,"current_useful_volume_percent":71.65,"ingress":6.547,"egress":4.498,"trend":"↑"},{"id":36,"basin_directorate":"БДДР","name":"Кокаляне","total_volume":null,"sanitary_volume":null,"current_volume":null,"current_volume_percent":null,"current_useful_volume":null,"current_useful_volume_percent":null,"ingress":null,"egress":null,"trend":null},{"id":37,"basin_directorate":"БДИБР","name":"Копринка","total_volume":142.214,"sanitary_volume":5.41,"current_volume":86.741,"current_volume_percent":60.99,"current_useful_volume":81.331,"current_useful_volume_percent":59.45,"ingress":12.555,"egress":1.4,"trend":"↑"},{"id":38,"basin_directorate":"БДИБР","name":"Белмекен","total_volume":144.036,"sanitary_volume":3.81,"current_volume":95.714,"current_volume_percent":66.45,"current_useful_volume":91.904,"current_useful_volume_percent":65.54,"ingress":null,"egress":null,"trend":"↓"},{"id":39,"basin_directorate":"БДИБР","name":"Чаира","total_volume":5.5,"sanitary_volume":1.369,"current_volume":2.891,"current_volume_percent":52.56,"current_useful_volume":1.522,"current_useful_volume_percent":36.84,"ingress":null,"egress":null,"trend":"↑"},{"id":40,"basin_directorate":"БДИБР","name":"Голям Беглик","total_volume":62.111,"sanitary_volume":3.942,"current_volume":55.985,"current_volume_percent":90.14,"current_useful_volume":52.043,"current_useful_volume_percent":89.47,"ingress":null,"egress":null,"trend":"↓"},{"id":41,"basin_directorate":"БДИБР","name":"Широка поляна","total_volume":23.98,"sanitary_volume":3.3,"current_volume":22.445,"current_volume_percent":93.6,"current_useful_volume":19.145,"current_useful_volume_percent":92.58,"ingress":null,"egress":null,"trend":"↑"},{"id":42,"basin_directorate":"БДИБР","name":"Беглика","total_volume":1.554,"sanitary_volume":0.242,"current_volume":1.34,"current_volume_percent":86.23,"current_useful_volume":1.098,"current_useful_volume_percent":83.69,"ingress":1.022,"egress":1.902,"trend":"↓"},{"id":43,"basin_directorate":"БДИБР","name":"Тошков Чарк","total_volume":1.782,"sanitary_volume":0.276,"current_volume":1.753,"current_volume_percent":98.37,"current_useful_volume":1.477,"current_useful_volume_percent":98.07,"ingress":1.235,"egress":1.501,"trend":"↓"},{"id":44,"basin_directorate":"БДИБР","name":"Батак","total_volume":310.298,"sanitary_volume":19.95,"current_volume":223.763,"current_volume_percent":72.11,"current_useful_volume":203.813,"current_useful_volume_percent":70.2,"ingress":14.88,"egress":9.479,"trend":"↑"},{"id":45,"basin_directorate":"БДЗБР","name":"Доспат","total_volume":449.249,"sanitary_volume":14.907,"current_volume":411.62,"current_volume_percent":91.62,"current_useful_volume":396.713,"current_useful_volume_percent":91.34,"ingress":18.556,"egress":7.505,"trend":"↑"},{"id":46,"basin_directorate":"БДИБР","name":"Цанков камък","total_volume":110.708,"sanitary_volume":31.2,"current_volume":104.736,"current_volume_percent":94.61,"current_useful_volume":73.536,"current_useful_volume_percent":92.49,"ingress":31.128,"egress":48.709,"trend":"↓"},{"id":47,"basin_directorate":"БДИБР","name":"Въча","total_volume":226.12,"sanitary_volume":24.52,"current_volume":221.096,"current_volume_percent":97.78,"current_useful_volume":196.576,"current_useful_volume_percent":97.51,"ingress":50.85,"egress":72.702,"trend":"↓"},{"id":48,"basin_directorate":"БДИБР","name":"Кричим","total_volume":20.256,"sanitary_volume":1.73,"current_volume":18.707,"current_volume_percent":92.35,"current_useful_volume":16.977,"current_useful_volume_percent":91.64,"ingress":72.591,"egress":69.628,"trend":"↑"},{"id":49,"basin_directorate":"БДИБР","name":"Кърджали","total_volume":497.236,"sanitary_volume":107.176,"current_volume":478.551,"current_volume_percent":96.24,"current_useful_volume":371.375,"current_useful_volume_percent":95.21,"ingress":40.616,"egress":104.32,"trend":"↓"},{"id":50,"basin_directorate":"БДИБР","name":"Студен кладенец","total_volume":387.772,"sanitary_volume":90.667,"current_volume":380.846,"current_volume_percent":98.21,"current_useful_volume":290.179,"current_useful_volume_percent":97.67,"ingress":125.081,"egress":128.275,"trend":"↓"},{"id":51,"basin_directorate":"БДИБР","name":"Ивайловград","total_volume":156.702,"sanitary_volume":59.526,"current_volume":129.503,"current_volume_percent":82.64,"current_useful_volume":69.977,"current_useful_volume_percent":72.01,"ingress":140.632,"egress":260.042,"trend":"↓"},{"id":52,"basin_directorate":"БДИБР","name":"Розов кладенец","total_volume":20.4,"sanitary_volume":13.268,"current_volume":18.024,"current_volume_percent":88.35,"current_useful_volume":4.756,"current_useful_volume_percent":66.69,"ingress":null,"egress":null,"trend":"~"}]